LICENSE
MANIFEST.in
README.md
VERSION
requirements.txt
setup.cfg
setup.py
examples/__init__.py
examples/flask_app.py
flask_quart_themes.egg-info/PKG-INFO
flask_quart_themes.egg-info/SOURCES.txt
flask_quart_themes.egg-info/dependency_links.txt
flask_quart_themes.egg-info/requires.txt
flask_quart_themes.egg-info/top_level.txt
flask_quart_themes.egg-info/zip-safe
flask_theming/__init__.py
flask_theming/clear_fix_flask.py
flask_theming/clear_fix_quart.py
flask_theming/decorators_flask.py
flask_theming/decorators_quart.py
flask_theming/jinja.py
flask_theming/model.py
flask_theming/setup_flask.py
flask_theming/setup_quart.py