Metadata-Version: 2.1
Name: flask-quart-themes
Version: 1.0.0
Summary: Themes support for Flask and Quart
Home-page: https://github.com/cr0hn/flask-quart-themes
Author: Daniel Garcia García
Author-email: cr0hn@cr0hn.com
License: License :: OSI Approved :: Apache Software License
Platform: UNKNOWN
Classifier: License :: OSI Approved :: Apache Software License
Classifier: Programming Language :: Python :: 3.10
Classifier: Programming Language :: Python :: 3.11
Classifier: Environment :: Console
Classifier: Operating System :: POSIX
Classifier: Operating System :: MacOS
Classifier: Operating System :: OS Independent
Classifier: Operating System :: Microsoft :: Windows
Classifier: Intended Audience :: Other Audience
Classifier: Intended Audience :: System Administrators
